doubt/__init__.py
doubt/datasets/__init__.py
doubt/datasets/airfoil.py
doubt/datasets/bike_sharing_daily.py
doubt/datasets/bike_sharing_hourly.py
doubt/datasets/blog.py
doubt/datasets/concrete.py
doubt/datasets/cpu.py
doubt/datasets/dataset.py
doubt/datasets/facebook_comments.py
doubt/datasets/facebook_metrics.py
doubt/datasets/fish_bioconcentration.py
doubt/datasets/fish_toxicity.py
doubt/datasets/forest_fire.py
doubt/datasets/gas_turbine.py
doubt/datasets/nanotube.py
doubt/datasets/new_taipei_housing.py
doubt/datasets/parkinsons.py
doubt/datasets/power_plant.py
doubt/datasets/protein.py
doubt/datasets/servo.py
doubt/datasets/solar_flare.py
doubt/datasets/space_shuttle.py
doubt/datasets/stocks.py
doubt/datasets/superconductivity.py
doubt/datasets/tehran_housing.py
doubt/datasets/yacht.py
doubt/models/__init__.py
doubt/models/boot/__init__.py
doubt/models/boot/boot.py
doubt/models/glm/__init__.py
doubt/models/glm/quantile_loss.py
doubt/models/glm/quantile_regressor.py
doubt/models/model.py
doubt/models/tree/__init__.py
doubt/models/tree/forest.py
doubt/models/tree/tree.py
doubt/models/tree/utils.py
doubt-6.0.0.dist-info/LICENSE
doubt-6.0.0.dist-info/METADATA
doubt-6.0.0.dist-info/WHEEL
doubt-6.0.0.dist-info/RECORD
