Metadata-Version: 2.1
Name: doubt
Version: 6.0.0
Summary: Bringing back uncertainty to machine learning.
Home-page: https://github.com/saattrupdan/doubt
License: MIT
Author: Dan Saattrup Nielsen
Author-email: saattrupdan@gmail.com
Requires-Python: >=3.9,<3.12
Classifier: License :: OSI Approved :: MIT License
Classifier: Programming Language :: Python :: 3
Classifier: Programming Language :: Python :: 3.9
Classifier: Programming Language :: Python :: 3.10
Classifier: Programming Language :: Python :: 3.11
Provides-Extra: all
Provides-Extra: datasets
Requires-Dist: joblib (>=1.2.0,<2.0.0)
Requires-Dist: numpy (>=1.23.0,<2.0.0)
Requires-Dist: openpyxl (>=3.0.10,<4.0.0) ; extra == "datasets" or extra == "all"
Requires-Dist: pandas (>=1.4.0,<3.0.0)
Requires-Dist: scikit-learn (>=1.1.0,<1.3.0)
Requires-Dist: scipy (>=1.10.0,<2.0.0)
Requires-Dist: tables (>=3.9.2,<4.0.0) ; extra == "datasets" or extra == "all"
Requires-Dist: tqdm (>=4.62.0,<5.0.0)
Requires-Dist: urllib3 (>=2.0.7,<3.0.0)
Requires-Dist: xlrd (>=2.0.1,<3.0.0) ; extra == "datasets" or extra == "all"
Project-URL: Repository, https://github.com/saattrupdan/doubt
